[
    {
        "id": 760030,
        "goodsDetail": {
            "id": 733879,
            "name": "爱尔兰韦沃牛奶香蕉口味200ml*12盒",
            "customCode": "5099869343927",
            "picUrl": "https://mailgoo.oss-cn-shenzhen.aliyuncs.com/pictures/2019_10_29/1572329193233.jpg",
            "displayPrice": 59.9,
            "mainCatId": 1057,
            "openId": null,
            "openCatId": null,
            "sourceId": 80,
            "sourceType": 1,
            "pool": null,
            "status": -4,
            "sort": 0,
            "unit": "箱",
            "editPicUrl": true,
            "onSale": true,
            "deliveryType": 1
        },
        "openId": null,
        "customCode": "5099869343927",
        "marketPrice": 59.9,
        "salePrice": 59.9,
        "costPrice": 47.5,
        "picUrl": null,
        "specInfos": {},
        "combination": {},
        "type": null,
        "num": -1,
        "realPrice": 59.9,
        "activity": null,
        "weight": 2.6,
        "taxRate": 13,
        "afterSaleType": 3,
        "discountRate": 0.793
    },
    {
        "id": 760031,
        "goodsDetail": {
            "id": 733880,
            "name": "【预售 2月22日发货】爱尔兰韦沃牛奶草莓口味200ml*12盒",
            "customCode": "5099869343910",
            "picUrl": "https://mailgoo.oss-cn-shenzhen.aliyuncs.com/pictures/2019_10_29/1572329012705.jpg",
            "displayPrice": 59.9,
            "mainCatId": 1057,
            "openId": null,
            "openCatId": null,
            "sourceId": 80,
            "sourceType": 1,
            "pool": null,
            "status": 1,
            "sort": 1,
            "unit": "箱",
            "editPicUrl": true,
            "onSale": true,
            "deliveryType": 1
        },
        "openId": null,
        "customCode": "5099869343910",
        "marketPrice": 59.9,
        "salePrice": 59.9,
        "costPrice": 47.5,
        "picUrl": null,
        "specInfos": {},
        "combination": {},
        "type": null,
        "num": 494,
        "realPrice": 59.9,
        "activity": null,
        "weight": 2.6,
        "taxRate": 13,
        "afterSaleType": 3,
        "discountRate": 0.793
    },
    {
        "id": 760036,
        "goodsDetail": {
            "id": 733885,
            "name": "【预售 2月22日发货】澳大利亚德运全脂纯牛奶200ml*12",
            "customCode": "9300639608549",
            "picUrl": "https://mailgoo.oss-cn-shenzhen.aliyuncs.com/pictures/2019_10_29/1572321685768.jpg",
            "displayPrice": 86,
            "mainCatId": 917,
            "openId": null,
            "openCatId": null,
            "sourceId": 80,
            "sourceType": 1,
            "pool": null,
            "status": 0,
            "sort": 1,
            "unit": "箱",
            "editPicUrl": true,
            "onSale": true,
            "deliveryType": 1
        },
        "openId": null,
        "customCode": "9300639608549",
        "marketPrice": 86,
        "salePrice": 86,
        "costPrice": 50.5,
        "picUrl": null,
        "specInfos": {},
        "combination": {},
        "type": null,
        "num": -1,
        "realPrice": 86,
        "activity": null,
        "weight": 2.8,
        "taxRate": 9,
        "afterSaleType": 3,
        "discountRate": 0.5872
    },
    {
        "id": 760039,
        "goodsDetail": {
            "id": 733888,
            "name": "澳大利亚进口德运脱脂奶粉1kg*2袋",
            "customCode": "930063999905-1",
            "picUrl": "https://mailgoo.oss-cn-shenzhen.aliyuncs.com/pictures/2019_10_29/1572322313684.jpg",
            "displayPrice": 158,
            "mainCatId": 925,
            "openId": null,
            "openCatId": null,
            "sourceId": 80,
            "sourceType": 1,
            "pool": null,
            "status": -1,
            "sort": 0,
            "unit": "袋",
            "editPicUrl": true,
            "onSale": true,
            "deliveryType": 1
        },
        "openId": null,
        "customCode": "930063999905-1",
        "marketPrice": 158,
        "salePrice": 158,
        "costPrice": 135,
        "picUrl": null,
        "specInfos": {},
        "combination": {},
        "type": null,
        "num": -1,
        "realPrice": 158,
        "activity": null,
        "weight": 2.2,
        "taxRate": 13,
        "afterSaleType": 3,
        "discountRate": 0.8544
    },
    {
        "id": 1279071,
        "goodsDetail": {
            "id": 1251550,
            "name": "简爱 饮用型•裸酸奶 原味（180g/瓶*12瓶）",
            "customCode": "6970618570162",
            "picUrl": "https://mailgoo.oss-cn-shenzhen.aliyuncs.com/pictures/2020_01_08/1578466277477.jpg",
            "displayPrice": 108,
            "mainCatId": 918,
            "openId": null,
            "openCatId": null,
            "sourceId": 94,
            "sourceType": 1,
            "pool": null,
            "status": -1,
            "sort": 1,
            "unit": "箱",
            "editPicUrl": true,
            "onSale": true,
            "deliveryType": 3
        },
        "openId": null,
        "customCode": "6970618570162",
        "marketPrice": 108,
        "salePrice": 108,
        "costPrice": 86.4,
        "picUrl": null,
        "specInfos": {
            "1箱": "1箱=180g*12瓶"
        },
        "combination": {},
        "type": null,
        "num": -1,
        "realPrice": 108,
        "activity": null,
        "weight": 2160,
        "taxRate": 13,
        "afterSaleType": 3,
        "discountRate": 0.8
    },
    {
        "id": 1279072,
        "goodsDetail": {
            "id": 1251551,
            "name": "预售2月19日起陆续发货  简爱 饮用型•原味家庭装（1.08kg/瓶*3瓶）",
            "customCode": "6970618570193",
            "picUrl": "https://mailgoo.oss-cn-shenzhen.aliyuncs.com/pictures/2020_01_08/1578466707345.jpg",
            "displayPrice": 98,
            "mainCatId": 918,
            "openId": null,
            "openCatId": null,
            "sourceId": 94,
            "sourceType": 1,
            "pool": null,
            "status": 1,
            "sort": 1,
            "unit": "箱",
            "editPicUrl": true,
            "onSale": true,
            "deliveryType": 3
        },
        "openId": null,
        "customCode": "6970618570193",
        "marketPrice": 98,
        "salePrice": 98,
        "costPrice": 78.4,
        "picUrl": null,
        "specInfos": {
            "1箱": "1箱=1.08kg*3瓶"
        },
        "combination": {},
        "type": null,
        "num": 805,
        "realPrice": 98,
        "activity": null,
        "weight": 3.24,
        "taxRate": 13,
        "afterSaleType": 3,
        "discountRate": 0.8
    },
    {
        "id": 1575249,
        "goodsDetail": {
            "id": 1547596,
            "name": "顶羊山羊奶250g*12",
            "customCode": "6935356703241",
            "picUrl": "https://mailgoo.oss-cn-shenzhen.aliyuncs.com/pictures/2020_04_07/1586248476683.jpg",
            "displayPrice": 87.1,
            "mainCatId": 919,
            "openId": null,
            "openCatId": null,
            "sourceId": 108,
            "sourceType": 1,
            "pool": null,
            "status": -1,
            "sort": 1,
            "unit": "箱",
            "editPicUrl": true,
            "onSale": true,
            "deliveryType": 1
        },
        "openId": null,
        "customCode": null,
        "marketPrice": 89,
        "salePrice": 88,
        "costPrice": 75,
        "picUrl": null,
        "specInfos": {
            "箱": "12*250g"
        },
        "combination": {},
        "type": null,
        "num": -1,
        "realPrice": 88,
        "activity": null,
        "weight": 3.5,
        "taxRate": 9,
        "afterSaleType": 3,
        "discountRate": 0.8523
    },
    {
        "id": 1603852,
        "goodsDetail": {
            "id": 1576201,
            "name": "新疆兵团花园黄金牧场纯牛奶20*200ml【预售 2月19日发货】",
            "customCode": "6912765081252",
            "picUrl": "https://mailgoo.oss-cn-shenzhen.aliyuncs.com/pictures/2020_04_07/1586248789403.jpg",
            "displayPrice": 88,
            "mainCatId": 917,
            "openId": null,
            "openCatId": null,
            "sourceId": 108,
            "sourceType": 1,
            "pool": null,
            "status": 1,
            "sort": 1,
            "unit": "箱",
            "editPicUrl": true,
            "onSale": true,
            "deliveryType": 1
        },
        "openId": null,
        "customCode": null,
        "marketPrice": 89,
        "salePrice": 88,
        "costPrice": 66,
        "picUrl": null,
        "specInfos": {
            "箱": "20*200ml"
        },
        "combination": {},
        "type": null,
        "num": 9628,
        "realPrice": 88,
        "activity": null,
        "weight": 5,
        "taxRate": 9,
        "afterSaleType": 3,
        "discountRate": 0.75
    }
]